{
  "baseline": null,
  "candidate": "88481c9d2da2bfbb67b9600565789a5c75f28469",
  "generatedAt": "2026-06-23T01:00:59.000Z",
  "lanes": [
    {
      "name": "candidate",
      "ref": "88481c9d2da2bfbb67b9600565789a5c75f28469",
      "status": "pass",
      "steps": [
        {
          "lane": "candidate",
          "name": "Banned account page after blocked sign-in",
          "screenshot": "screenshots/account-banned-page.png",
          "slug": "account-banned-page",
          "status": "pass"
        }
      ]
    }
  ],
  "mode": "feature",
  "outputDir": "/tmp/clawhub-banned-proof-hYjWLS",
  "provider": "local",
  "scenario": "e2e/local-auth/malicious-skill-ban-flow.pw.test.ts",
  "status": "pass"
}
